{"data":{"allMdx":{"edges":[{"node":{"fields":{"slug":"/projects/jadedgamer/"},"frontmatter":{"color":"952067","guid":"901","title":"Jaded Gamer","size":"col-md-4","description":"A video game news aggregator"}}},{"node":{"fields":{"slug":"/projects/alifewellplayed/"},"frontmatter":{"color":"952067","guid":"901","title":"A Life Well Played","size":"col-md-4","description":"Just your typical blog"}}},{"node":{"fields":{"slug":"//portfolio/gamehackers/"},"frontmatter":{"color":"952067","guid":"201","title":"Gamehackers.net","size":"col-md-4","description":"A website"}}},{"node":{"fields":{"slug":"//portfolio/gmachina/"},"frontmatter":{"color":"952067","guid":null,"title":"gMachina","size":"col-md-4","description":"A REST based API game backbone"}}},{"node":{"fields":{"slug":"/projects/magnolia/"},"frontmatter":{"color":"952067","guid":"901","title":"Magnolia","size":"col-md-4","description":"A video game of sorts."}}},{"node":{"fields":{"slug":"/projects/tyler-camera/"},"frontmatter":{"color":"952067","guid":"901","title":"Tyler.Camera","size":"col-md-4","description":"A photo blog of sorts."}}}]}}}